<OpenSearchDescription xmlns:moz="http://www.mozilla.org/2006/browser/search/"
                       xmlns="http://a9.com/-/spec/opensearch/1.1/">
    <ShortName>{{go}}</ShortName>
    <Description>Private shortlinks on your tailnet</Description>
    <InputEncoding>UTF-8</InputEncoding>
    <Image width="16" height="16" type="image/png">{{.Scheme}}://{{go}}/.static/favicon.png</Image>
    <Url type="text/html" method="get" template="{{.Scheme}}://{{go}}/{searchTerms}"/>
    <moz:SearchForm>{{.Scheme}}://{{go}}/</moz:SearchForm>
</OpenSearchDescription>
